nasa/__init__.py
nasa/auth.py
nasa/decorators.py
nasa/exceptions.py
nasa/typing.py
nasa/utils.py
nasa/warnings.py
python_nasa-0.3.1.dist-info/LICENSE
python_nasa-0.3.1.dist-info/METADATA
python_nasa-0.3.1.dist-info/WHEEL
python_nasa-0.3.1.dist-info/top_level.txt
python_nasa-0.3.1.dist-info/RECORD
